ijson_bigint.libs/libyajl-6e683ecb.so.2.1.1
ijson/dump.py
ijson/utils35.py
ijson/version.py
ijson/utils.py
ijson/common.py
ijson/compat.py
ijson/__init__.py
ijson/backends/yajl2.py
ijson/backends/yajl2_cffi.py
ijson/backends/yajl.py
ijson/backends/python.py
ijson/backends/_yajl2.cpython-311-aarch64-linux-musl.so
ijson/backends/_yajl2_ctypes_common.py
ijson/backends/yajl2_c.py
ijson/backends/__init__.py
ijson_bigint-3.2.0.post1.dist-info/top_level.txt
ijson_bigint-3.2.0.post1.dist-info/LICENSE.txt
ijson_bigint-3.2.0.post1.dist-info/RECORD
ijson_bigint-3.2.0.post1.dist-info/METADATA
ijson_bigint-3.2.0.post1.dist-info/WHEEL
