Metadata-Version: 2.1
Name: ijson-bigint
Version: 3.2.0.post1
Summary: Iterative JSON parser with standard Python iterator interfaces
Home-page: https://github.com/jbinary/ijson
Author: Rodrigo Tobar, Ivan Sagalaev, Sergey Dobrov
Author-email: rtobar@icrar.org, maniac@softwaremaniacs.org
License: BSD
Platform: UNKNOWN
Classifier: Development Status :: 5 - Production/Stable
Classifier: License :: OSI Approved :: BSD License
Classifier: Programming Language :: Python :: 2.7
Classifier: Programming Language :: Python :: 3.4
Classifier: Programming Language :: Python :: 3.5
Classifier: Programming Language :: Python :: 3.6
Classifier: Programming Language :: Python :: 3.7
Classifier: Programming Language :: Python :: 3.8
Classifier: Programming Language :: Python :: 3.9
Classifier: Programming Language :: Python :: 3.10
Classifier: Programming Language :: Python :: 3.11
Classifier: Programming Language :: Python :: Implementation :: CPython
Classifier: Programming Language :: Python :: Implementation :: PyPy
Classifier: Topic :: Software Development :: Libraries :: Python Modules
